[
  {
    "title": "SINNER ATROPELA COMPATRIOTA E AMPLIA SEQUÊNCIA HISTÓRICA EM ROMA",
    "url": "https://www.radio520.com.br"
  },
  {
    "title": "THUNDER ATROPELA LAKERS E VARRE SÉRIE: DINASTIA EM CONSTRUÇÃO?",
    "url": "https://www.radio520.com.br"
  },
  {
    "title": "BOTAFOGO AFUNDA EM DÍVIDAS E LEVA TERCEIRO TRANSFER BAN DA FIFA",
    "url": "https://www.radio520.com.br"
  },
  {
    "title": "MBAPPÉ DESAFIA CRÍTICAS E QUER VOLTAR JÁ AO REAL MADRID",
    "url": "https://www.radio520.com.br"
  }
]
